README.md
setup.py
hbmqtt_auth_home_assistant/__init__.py
hbmqtt_auth_home_assistant.egg-info/PKG-INFO
hbmqtt_auth_home_assistant.egg-info/SOURCES.txt
hbmqtt_auth_home_assistant.egg-info/dependency_links.txt
hbmqtt_auth_home_assistant.egg-info/entry_points.txt
hbmqtt_auth_home_assistant.egg-info/requires.txt
hbmqtt_auth_home_assistant.egg-info/top_level.txt