Metadata-Version: 1.1
Name: hbmqtt-auth-home-assistant
Version: 1.0.1
Summary: HBMQTT Authentication plugin for Home Assistant
Home-page: https://github.com/home-assistant/hbmqtt-auth-home-assistant
Author: Paulus Schoutsen
Author-email: paulus@home-assistant.io
License: Apache License 2.0
Platform: all
Classifier: Programming Language :: Python :: 3.5
Classifier: Programming Language :: Python :: 3.6
